{
  "contract_version": "2026-06-06.1",
  "generated_at": "1970-01-01T00:00:00.000Z",
  "name": "Allways",
  "netuid": 7,
  "schema_version": 1,
  "slug": "allways",
  "summary": {
    "avg_latency_ms": 214,
    "degraded_count": 0,
    "failed_count": 0,
    "last_checked": "2026-06-06T08:57:55.349Z",
    "last_ok": "2026-06-06T08:57:55.349Z",
    "name": "Allways",
    "netuid": 7,
    "ok_count": 14,
    "slug": "allways",
    "status": "ok",
    "surface_count": 14,
    "unknown_count": 0
  },
  "surfaces": [
    {
      "auth_required": false,
      "classification": "live",
      "content_type": "application/json; charset=utf-8",
      "error": null,
      "error_class": null,
      "kind": "subnet-api",
      "last_checked": "2026-06-06T08:57:54.856Z",
      "last_ok": "2026-06-06T08:57:54.856Z",
      "latency_ms": 158,
      "method_tested": "GET",
      "netuid": 7,
      "private_redirect_blocked": false,
      "provider": "allways",
      "public_safe": true,
      "redirect_target": null,
      "status": "ok",
      "status_code": 200,
      "subnet_name": "Allways",
      "subnet_slug": "allways",
      "surface_id": "allways-api-health",
      "uptime_sample_ratio": 1,
      "url": "https://api.all-ways.io/health",
      "verified_at": "2026-06-06T08:57:54.856Z"
    },
    {
      "auth_required": false,
      "classification": "live",
      "content_type": "application/json; charset=utf-8",
      "error": null,
      "error_class": null,
      "kind": "subnet-api",
      "last_checked": "2026-06-06T08:57:54.878Z",
      "last_ok": "2026-06-06T08:57:54.878Z",
      "latency_ms": 176,
      "method_tested": "GET",
      "netuid": 7,
      "private_redirect_blocked": false,
      "provider": "allways",
      "public_safe": true,
      "redirect_target": null,
      "status": "ok",
      "status_code": 200,
      "subnet_name": "Allways",
      "subnet_slug": "allways",
      "surface_id": "allways-crown",
      "uptime_sample_ratio": 1,
      "url": "https://api.all-ways.io/crown",
      "verified_at": "2026-06-06T08:57:54.878Z"
    },
    {
      "auth_required": false,
      "classification": "live",
      "content_type": "text/html;charset=utf-8",
      "error": null,
      "error_class": null,
      "kind": "docs",
      "last_checked": "2026-06-06T08:57:55.050Z",
      "last_ok": "2026-06-06T08:57:55.050Z",
      "latency_ms": 320,
      "method_tested": "GET",
      "netuid": 7,
      "private_redirect_blocked": false,
      "provider": "allways",
      "public_safe": true,
      "redirect_target": null,
      "status": "ok",
      "status_code": 200,
      "subnet_name": "Allways",
      "subnet_slug": "allways",
      "surface_id": "allways-docs",
      "uptime_sample_ratio": 1,
      "url": "https://docs.all-ways.io/how-it-works.html",
      "verified_at": "2026-06-06T08:57:55.050Z"
    },
    {
      "auth_required": false,
      "classification": "live",
      "content_type": "application/json; charset=utf-8",
      "error": null,
      "error_class": null,
      "kind": "subnet-api",
      "last_checked": "2026-06-06T08:57:54.894Z",
      "last_ok": "2026-06-06T08:57:54.894Z",
      "latency_ms": 153,
      "method_tested": "GET",
      "netuid": 7,
      "private_redirect_blocked": false,
      "provider": "allways",
      "public_safe": true,
      "redirect_target": null,
      "status": "ok",
      "status_code": 200,
      "subnet_name": "Allways",
      "subnet_slug": "allways",
      "surface_id": "allways-events-latest",
      "uptime_sample_ratio": 1,
      "url": "https://api.all-ways.io/events/latest",
      "verified_at": "2026-06-06T08:57:54.894Z"
    },
    {
      "auth_required": false,
      "classification": "live",
      "content_type": "application/json; charset=utf-8",
      "error": null,
      "error_class": null,
      "kind": "subnet-api",
      "last_checked": "2026-06-06T08:57:54.933Z",
      "last_ok": "2026-06-06T08:57:54.933Z",
      "latency_ms": 144,
      "method_tested": "GET",
      "netuid": 7,
      "private_redirect_blocked": false,
      "provider": "allways",
      "public_safe": true,
      "redirect_target": null,
      "status": "ok",
      "status_code": 200,
      "subnet_name": "Allways",
      "subnet_slug": "allways",
      "surface_id": "allways-miners",
      "uptime_sample_ratio": 1,
      "url": "https://api.all-ways.io/miners",
      "verified_at": "2026-06-06T08:57:54.933Z"
    },
    {
      "auth_required": false,
      "classification": "live",
      "content_type": "application/json; charset=utf-8",
      "error": null,
      "error_class": null,
      "kind": "subnet-api",
      "last_checked": "2026-06-06T08:57:55.349Z",
      "last_ok": "2026-06-06T08:57:55.349Z",
      "latency_ms": 551,
      "method_tested": "GET",
      "netuid": 7,
      "private_redirect_blocked": false,
      "provider": "allways",
      "public_safe": true,
      "redirect_target": null,
      "status": "ok",
      "status_code": 200,
      "subnet_name": "Allways",
      "subnet_slug": "allways",
      "surface_id": "allways-miners-leaderboard",
      "uptime_sample_ratio": 1,
      "url": "https://api.all-ways.io/miners/leaderboard",
      "verified_at": "2026-06-06T08:57:55.349Z"
    },
    {
      "auth_required": false,
      "classification": "live",
      "content_type": "application/json; charset=utf-8",
      "error": null,
      "error_class": null,
      "kind": "subnet-api",
      "last_checked": "2026-06-06T08:57:54.955Z",
      "last_ok": "2026-06-06T08:57:54.955Z",
      "latency_ms": 145,
      "method_tested": "GET",
      "netuid": 7,
      "private_redirect_blocked": false,
      "provider": "allways",
      "public_safe": true,
      "redirect_target": null,
      "status": "ok",
      "status_code": 200,
      "subnet_name": "Allways",
      "subnet_slug": "allways",
      "surface_id": "allways-miners-reliability",
      "uptime_sample_ratio": 1,
      "url": "https://api.all-ways.io/miners/reliability",
      "verified_at": "2026-06-06T08:57:54.955Z"
    },
    {
      "auth_required": false,
      "classification": "live",
      "content_type": "application/json; charset=utf-8",
      "error": null,
      "error_class": null,
      "kind": "subnet-api",
      "last_checked": "2026-06-06T08:57:55.072Z",
      "last_ok": "2026-06-06T08:57:55.072Z",
      "latency_ms": 240,
      "method_tested": "GET",
      "netuid": 7,
      "private_redirect_blocked": false,
      "provider": "allways",
      "public_safe": true,
      "redirect_target": null,
      "status": "ok",
      "status_code": 200,
      "subnet_name": "Allways",
      "subnet_slug": "allways",
      "surface_id": "allways-network-overview",
      "uptime_sample_ratio": 1,
      "url": "https://api.all-ways.io/network/overview",
      "verified_at": "2026-06-06T08:57:55.072Z"
    },
    {
      "auth_required": false,
      "classification": "live",
      "content_type": "application/json; charset=utf-8",
      "error": null,
      "error_class": null,
      "kind": "subnet-api",
      "last_checked": "2026-06-06T08:57:55.002Z",
      "last_ok": "2026-06-06T08:57:55.002Z",
      "latency_ms": 159,
      "method_tested": "GET",
      "netuid": 7,
      "private_redirect_blocked": false,
      "provider": "allways",
      "public_safe": true,
      "redirect_target": null,
      "status": "ok",
      "status_code": 200,
      "subnet_name": "Allways",
      "subnet_slug": "allways",
      "surface_id": "allways-protocol-chain-state",
      "uptime_sample_ratio": 1,
      "url": "https://api.all-ways.io/protocol/chain-state",
      "verified_at": "2026-06-06T08:57:55.002Z"
    },
    {
      "auth_required": false,
      "classification": "live",
      "content_type": "application/json; charset=utf-8",
      "error": null,
      "error_class": null,
      "kind": "subnet-api",
      "last_checked": "2026-06-06T08:57:55.001Z",
      "last_ok": "2026-06-06T08:57:55.001Z",
      "latency_ms": 144,
      "method_tested": "GET",
      "netuid": 7,
      "private_redirect_blocked": false,
      "provider": "allways",
      "public_safe": true,
      "redirect_target": null,
      "status": "ok",
      "status_code": 200,
      "subnet_name": "Allways",
      "subnet_slug": "allways",
      "surface_id": "allways-protocol-constants",
      "uptime_sample_ratio": 1,
      "url": "https://api.all-ways.io/protocol/constants",
      "verified_at": "2026-06-06T08:57:55.001Z"
    },
    {
      "auth_required": false,
      "classification": "live",
      "content_type": "text/html; charset=utf-8",
      "error": null,
      "error_class": null,
      "kind": "source-repo",
      "last_checked": "2026-06-06T08:57:55.317Z",
      "last_ok": "2026-06-06T08:57:55.317Z",
      "latency_ms": 439,
      "method_tested": "HEAD",
      "netuid": 7,
      "private_redirect_blocked": false,
      "provider": "allways",
      "public_safe": true,
      "redirect_target": null,
      "status": "ok",
      "status_code": 200,
      "subnet_name": "Allways",
      "subnet_slug": "allways",
      "surface_id": "allways-source-repo",
      "uptime_sample_ratio": 1,
      "url": "https://github.com/entrius/allways",
      "verified_at": "2026-06-06T08:57:55.317Z"
    },
    {
      "auth_required": false,
      "classification": "live",
      "content_type": "text/event-stream",
      "error": null,
      "error_class": null,
      "kind": "sse",
      "last_checked": "2026-06-06T08:57:54.955Z",
      "last_ok": "2026-06-06T08:57:54.955Z",
      "latency_ms": 60,
      "method_tested": "GET",
      "netuid": 7,
      "private_redirect_blocked": false,
      "provider": "allways",
      "public_safe": true,
      "redirect_target": null,
      "status": "ok",
      "status_code": 200,
      "subnet_name": "Allways",
      "subnet_slug": "allways",
      "surface_id": "allways-sse",
      "uptime_sample_ratio": 1,
      "url": "https://api.all-ways.io/sse",
      "verified_at": "2026-06-06T08:57:54.955Z"
    },
    {
      "auth_required": false,
      "classification": "live",
      "content_type": "text/html; charset=utf-8",
      "error": null,
      "error_class": null,
      "kind": "openapi",
      "last_checked": "2026-06-06T08:57:54.976Z",
      "last_ok": "2026-06-06T08:57:54.976Z",
      "latency_ms": 62,
      "method_tested": "GET",
      "netuid": 7,
      "private_redirect_blocked": false,
      "provider": "allways",
      "public_safe": true,
      "redirect_target": null,
      "status": "ok",
      "status_code": 200,
      "subnet_name": "Allways",
      "subnet_slug": "allways",
      "surface_id": "allways-swagger",
      "uptime_sample_ratio": 1,
      "url": "https://api.all-ways.io/swagger",
      "verified_at": "2026-06-06T08:57:54.976Z"
    },
    {
      "auth_required": false,
      "classification": "live",
      "content_type": "text/html",
      "error": null,
      "error_class": null,
      "kind": "website",
      "last_checked": "2026-06-06T08:57:55.162Z",
      "last_ok": "2026-06-06T08:57:55.162Z",
      "latency_ms": 240,
      "method_tested": "HEAD",
      "netuid": 7,
      "private_redirect_blocked": false,
      "provider": "allways",
      "public_safe": true,
      "redirect_target": null,
      "status": "ok",
      "status_code": 200,
      "subnet_name": "Allways",
      "subnet_slug": "allways",
      "surface_id": "allways-website",
      "uptime_sample_ratio": 1,
      "url": "https://all-ways.io/",
      "verified_at": "2026-06-06T08:57:55.162Z"
    }
  ]
}
